arclet/alconna_cli/__init__.py
arclet/alconna_cli/__main__.py
arclet/alconna_cli/plugins/__init__.py
arclet/alconna_cli/plugins/analysis.py
arclet/alconna_cli/plugins/cache.py
arclet/alconna_cli/plugins/create.py
arclet/alconna_cli/plugins/lang.py
arclet/alconna_cli/plugins/using.py
arclet_alconna_cli-0.3.1.dist-info/entry_points.txt
arclet_alconna_cli-0.3.1.dist-info/WHEEL
arclet_alconna_cli-0.3.1.dist-info/METADATA
arclet_alconna_cli-0.3.1.dist-info/license_files/LICENSE
arclet_alconna_cli-0.3.1.dist-info/RECORD
